{
  "meta": {
    "version": "1.0.0",
    "created": "2026-04-01",
    "source": "双交易宝典"
  },
  "red_book": {
    "name": "红色交易宝典",
    "pages": 131,
    "categories": {
      "K线基础": {
        "description": "K线基础知识与技术分析入门",
        "key_concepts": [
          "阳线：收盘价高于开盘价，红色或空心",
          "阴线：收盘价低于开盘价，黑色或实心",
          "上影线：最高价与实体上端的距离",
          "下影线：最低价与实体下端的距离",
          "实体：开盘价与收盘价之间的部分"
        ],
        "k线形态": {
          "光头光脚大阳线": "强烈涨势，实体越长多方实力越强",
          "光头光脚大阴线": "强烈跌势，实体越长空方实力越强",
          "上影阳线": "高位遇卖压，后市看跌",
          "下影阳线": "多方攻击沉稳，先跌后涨",
          "十字星": "变盘信号，趋势即将改变"
        }
      },
      "均线系统": {
        "description": "移动平均线MA分析系统",
        "均线类型": {
          "MA5": "周线，短期趋势",
          "MA10": "半月线，短期趋势",
          "MA20": "月线，中期趋势",
          "MA60": "季线，中长期趋势",
          "MA120": "半年线，长期趋势",
          "MA240": "年线，长期趋势"
        },
        "买卖信号": {
          "金叉": "短期均线上穿长期均线，看涨信号",
          "死叉": "短期均线下穿长期均线，看跌信号",
          "多头排列": "MA5>MA10>MA20>MA60，牛市格局",
          "空头排列": "MA5<MA10<MA20<MA60，熊市格局"
        }
      },
      "MACD指标": {
        "description": "指数平滑异同移动平均线",
        "构成": {
          "DIFF": "快线，EMA(12)-EMA(26)",
          "DEA": "慢线，DIFF的EMA(9)",
          "BAR": "能量柱，2*(DIFF-DEA)"
        },
        "交易信号": {
          "金叉": "DIFF上穿DEA，买入信号",
          "死叉": "DIFF下穿DEA，卖出信号",
          "顶背离": "价格创新高但MACD未创新高，看跌",
          "底背离": "价格创新低但MACD未创新低，看涨"
        },
        "战法": {
          "双龙探底": "MACD零轴下方短期内出现2次金叉，买入机会",
          "佛手向上": "DIF与DEA金叉后回调再反转向上",
          "小鸭出水": "DIF在0轴下方金叉DEA后回落再金叉"
        }
      },
      "KDJ指标": {
        "description": "随机指标，适用于中短期趋势分析",
        "参数范围": {
          "K值": "0-100，快线",
          "D值": "0-100，慢线",
          "J值": "可超过100或低于0，最快"
        },
        "超买超卖": {
          "KDJ>80": "超买状态，考虑卖出",
          "KDJ<20": "超卖状态，考虑买入",
          "KDJ在50附近": "多空力量均衡"
        }
      },
      "RSI指标": {
        "description": "相对强弱指数，衡量买卖双方强度",
        "计算公式": "RSI = 价格涨幅平均值 / (价格涨幅平均值 + 价格跌幅平均值)",
        "参数设置": {
          "RSI6": "短期波动",
          "RSI12": "中期趋势",
          "RSI24": "长期趋势"
        },
        "交易规则": {
          "RSI>80": "超买，分批卖出",
          "RSI<20": "超卖，分批建仓",
          "RSI以50为界": ">50多头，<50空头"
        }
      },
      "布林线BOLL": {
        "description": "价格通道指标，显示价格波动范围",
        "构成": {
          "上轨": "中轨+2*标准差",
          "中轨": "20日移动平均线",
          "下轨": "中轨-2*标准差"
        },
        "交易策略": {
          "三线向上": "强势上涨，买在中轨卖在上轨",
          "三线向下": "弱势下跌，卖在中轨买在下轨",
          "开口放大": "趋势加速，顺势操作",
          "缩口收敛": "趋势酝酿，观望等待方向选择"
        }
      },
      "成交量分析": {
        "description": "成交量是仅次于价格的分析依据",
        "量价关系": {
          "量增价涨": "上涨动能增强，趋势向好",
          "量增价跌": "下跌动能增强，趋势向弱",
          "量缩价涨": "上涨动能不足，可能见顶",
          "量缩价跌": "下跌动能减缓，可能见底"
        },
        "换手率": {
          "<1%": "低量水平，市场冷清",
          "3%-7%": "相对活跃",
          "7%-10%": "强势股，高度活跃",
          ">15%": "大庄操作，可能成为黑马"
        }
      },
      "交易流程": {
        "description": "正确的交易执行流程",
        "步骤": [
          "1. 整理盘面：发现趋势、观察位置、等待信号",
          "2. 计划交易：预设开仓、止损、止盈方案",
          "3. 执行交易：严格按计划执行，控制情绪",
          "4. 交易记录：复盘总结，持续改进"
        ],
        "核心要素": {
          "概率": "成功率，通过技术分析提高",
          "盈亏比": "止盈/止损比例，建议≥1:4",
          "仓位管理": "控制风险，避免爆仓"
        }
      }
    }
  },
  "yellow_book": {
    "name": "黄色交易宝典",
    "pages": 125,
    "categories": {
      "趋势分析": {
        "description": "趋势是交易的核心，顺势而为",
        "趋势类型": {
          "上升趋势": "峰谷依次上移，价格不断创新高",
          "下降趋势": "峰谷依次下移，价格不断创新低",
          "横盘整理": "价格在区间内震荡，方向不明"
        },
        "峰级概念": {
          "峰": "顺势突前产生的拐点，代表趋势方向",
          "级": "反弹回调形成的拐点，相对固定",
          "破级": "价格越过级位，趋势反转信号"
        },
        "交易原则": {
          "趋势延续": "价格不断创新峰",
          "趋势反转": "价格破级",
          "持仓规则": "不破级不走"
        }
      },
      "位置分析": {
        "description": "探寻关键位置，构筑支撑压力",
        "趋势线画法": {
          "上升趋势线": "连接最低点与最高点之前的任意低点",
          "下降趋势线": "连接最高点与最低点之前的任意高点",
          "原则": "不穿越价位、时间跨度足够、点越多越有效"
        },
        "黄金分割": {
          "0.382": "弱势回调位",
          "0.5": "中等回调位",
          "0.618": "强势回调位"
        }
      },
      "形态分析": {
        "description": "形态是价格走势的规律总结",
        "反转形态": {
          "V形反转": "直上直下，剧烈波动时出现",
          "W底(双底)": "两次探底不破，突破颈线看涨",
          "M头(双顶)": "两次探顶不破，跌破颈线看跌",
          "头肩底": "左肩-头-右肩，突破颈线看涨",
          "头肩顶": "左肩-头-右肩，跌破颈线看跌"
        },
        "持续形态": {
          "三角形": "对称/上升/下降三角形",
          "旗形": "上升旗形看涨，下降旗形看跌",
          "楔形": "上升楔形看跌，下降楔形看涨"
        }
      },
      "K线信号": {
        "description": "K线组合分析，识别买卖点",
        "单K信号": {
          "大阳线": "强烈涨势",
          "大阴线": "强烈跌势",
          "十字星": "变盘信号",
          "射击之星": "顶部反转",
          "吊颈线": "顶部反转"
        },
        "双K组合": {
          "延续性组合": "两根同向K线顺向前移",
          "竭止性组合": "推进无力，即将停止",
          "逆转性组合": "掉头信号，可能反转"
        },
        "三K组合": {
          "早晨之星": "底部反转信号",
          "黄昏之星": "顶部反转信号",
          "红三兵": "连续三阳，看涨",
          "黑三兵": "连续三阴，看跌"
        }
      },
      "交易心法": {
        "description": "交易的核心心法与纪律",
        "核心理念": [
          "应无所住而生其心",
          "不预测只识别，不预判只跟随",
          "心不住于涨跌，不住于多空，不住于盈亏",
          "直观屏息，一念不生，湛于末时",
          "以K线为相，以量价为证，以结构为凭"
        ],
        "执行纪律": [
          "严格止损，控制大亏",
          "仓位管理，心态稳定",
          "顺势而为，不逆势操作",
          "等待信号，不盲目入场"
        ]
      }
    }
  }
}